tf_registry/__init__.py
tf_registry-1.0.0.dist-info/LICENSE
tf_registry-1.0.0.dist-info/METADATA
tf_registry-1.0.0.dist-info/WHEEL
tf_registry-1.0.0.dist-info/top_level.txt
tf_registry-1.0.0.dist-info/RECORD
